neko/__init__.py
neko/colorstr.py
neko/esl.py
neko/mysql.py
neko/procbar.py
neko/redisCluterBee.py
neko/ssh.py
neko/tcpdump.py
pyFneko-3.6.dist-info/DESCRIPTION.rst
pyFneko-3.6.dist-info/METADATA
pyFneko-3.6.dist-info/RECORD
pyFneko-3.6.dist-info/WHEEL
pyFneko-3.6.dist-info/metadata.json
pyFneko-3.6.dist-info/top_level.txt
tests/__init__.py
tests/neko_test.py
